iocsearcher/__main__.py
iocsearcher/doc_base.py
iocsearcher/doc_common.py
iocsearcher/doc_ehtml.py
iocsearcher/doc_epdf.py
iocsearcher/doc_html.py
iocsearcher/doc_pdf.py
iocsearcher/doc_word.py
iocsearcher/document.py
iocsearcher/ioc.py
iocsearcher/searcher.py
iocsearcher/data/iana_schemes.txt
iocsearcher/data/patterns.ini
iocsearcher/data/tlds-alpha-by-domain.txt
iocsearcher/monero/LICENSE.txt
iocsearcher/monero/base58.py
iocsearcher-2.7.2.dist-info/licenses/LICENSE
iocsearcher-2.7.2.dist-info/METADATA
iocsearcher-2.7.2.dist-info/WHEEL
iocsearcher-2.7.2.dist-info/entry_points.txt
iocsearcher-2.7.2.dist-info/top_level.txt
iocsearcher-2.7.2.dist-info/RECORD
