Metadata-Version: 2.4
Name: iocsearcher
Version: 2.7.2
Summary: A library and command line tool for extracting indicators of compromise (IOCs) from security reports in PDF, HTML, or text formats.
Author: MaliciaLab
License: MIT License
Project-URL: Homepage, https://github.com/malicialab/iocsearcher
Keywords: ioc,indicator of compromise,cyber observable,security,threat reports,pdf,html
Classifier: License :: OSI Approved :: MIT License
Classifier: Programming Language :: Python
Classifier: Programming Language :: Python :: 3
Classifier: Topic :: Security
License-File: LICENSE
Requires-Dist: base58
Requires-Dist: beautifulsoup4
Requires-Dist: bech32
Requires-Dist: cashaddress
Requires-Dist: cbor
Requires-Dist: docx2python
Requires-Dist: eth-hash[pycryptodome]
Requires-Dist: intervaltree
Requires-Dist: langdetect
Requires-Dist: lxml
Requires-Dist: pdfminer.six
Requires-Dist: phonenumbers
Requires-Dist: python-magic
Requires-Dist: readabilipy
Requires-Dist: solders
Dynamic: license-file
